<?xml version="1.0"?>
<!DOCTYPE hibernate-mapping PUBLIC "-//Hibernate/Hibernate Mapping DTD 3.0//EN"
"http://www.hibernate.org/dtd/hibernate-mapping-3.0.dtd">
<!-- Generated Sep 5, 2015 1:43:34 PM by Hibernate Tools 4.3.1.Final -->
<hibernate-mapping>
    <class name="edu.tamu.ctv.entity.Resultshistory" table="resultshistory" schema="public" optimistic-lock="version">
		<id name="id" type="long">
			<column name="id" />
			<generator class="sequence">
				<param name="sequence">resultshistory_id_seq</param>
			</generator>
		</id>
        <many-to-one name="results" class="edu.tamu.ctv.entity.Results" fetch="select">
            <column name="results" not-null="true" />
        </many-to-one>
        <many-to-one name="users" class="edu.tamu.ctv.entity.Users" fetch="select">
            <column name="updatedby" not-null="true" />
        </many-to-one>
        <property name="oldstrresult" type="string">
            <column name="oldstrresult" />
        </property>
        <property name="newstrresult" type="string">
            <column name="newstrresult" />
        </property>
        <property name="updateddt" type="timestamp">
            <column name="updateddt" length="29" not-null="true" />
        </property>
    </class>
</hibernate-mapping>
